konfigure/__init__.py
konfigure/core.py
konfigure/tests/__init__.py
konfigure/tests/test_advanced_features.py
konfigure/tests/test_core.py
konfigure-0.1.7.dist-info/METADATA
konfigure-0.1.7.dist-info/WHEEL
konfigure-0.1.7.dist-info/top_level.txt
konfigure-0.1.7.dist-info/RECORD
