Metadata-Version: 2.4
Name: konfigure
Version: 0.1.7
Summary: A YAML-based configuration management tool for separating code from prompts in LLMs
Home-page: https://github.com/sunnybak/konfigure
Author: Konfigure Team
Author-email: example@example.com
License: MIT
Requires-Python: >=3.7
Requires-Dist: pyyaml>=6.0
Requires-Dist: jinja2>=3.0.0
Provides-Extra: dev
Requires-Dist: pytest>=7.0.0; extra == "dev"
Requires-Dist: black>=23.0.0; extra == "dev"
Requires-Dist: isort>=5.0.0; extra == "dev"
Dynamic: author
Dynamic: author-email
Dynamic: home-page
Dynamic: requires-python
